litegram/__init__.py
litegram/__main__.py
litegram/__meta__.py
litegram/exceptions.py
litegram/loggers.py
litegram/py.typed
litegram/cli/__init__.py
litegram/cli/main.py
litegram/client/__init__.py
litegram/client/bot.py
litegram/client/context_controller.py
litegram/client/default.py
litegram/client/telegram.py
litegram/client/session/__init__.py
litegram/client/session/base.py
litegram/client/session/httpx.py
litegram/client/session/middlewares/__init__.py
litegram/client/session/middlewares/base.py
litegram/client/session/middlewares/manager.py
litegram/client/session/middlewares/request_logging.py
litegram/dispatcher/__init__.py
litegram/dispatcher/dispatcher.py
litegram/dispatcher/flags.py
litegram/dispatcher/router.py
litegram/dispatcher/event/__init__.py
litegram/dispatcher/event/bases.py
litegram/dispatcher/event/event.py
litegram/dispatcher/event/handler.py
litegram/dispatcher/event/telegram.py
litegram/dispatcher/middlewares/__init__.py
litegram/dispatcher/middlewares/base.py
litegram/dispatcher/middlewares/data.py
litegram/dispatcher/middlewares/error.py
litegram/dispatcher/middlewares/manager.py
litegram/dispatcher/middlewares/user_context.py
litegram/enums/__init__.py
litegram/enums/bot_command_scope_type.py
litegram/enums/chat_action.py
litegram/enums/chat_boost_source_type.py
litegram/enums/chat_member_status.py
litegram/enums/chat_type.py
litegram/enums/content_type.py
litegram/enums/currency.py
litegram/enums/dice_emoji.py
litegram/enums/encrypted_passport_element.py
litegram/enums/inline_query_result_type.py
litegram/enums/input_media_type.py
litegram/enums/input_paid_media_type.py
litegram/enums/input_profile_photo_type.py
litegram/enums/input_story_content_type.py
litegram/enums/keyboard_button_poll_type_type.py
litegram/enums/mask_position_point.py
litegram/enums/menu_button_type.py
litegram/enums/message_entity_type.py
litegram/enums/message_origin_type.py
litegram/enums/owned_gift_type.py
litegram/enums/paid_media_type.py
litegram-1.0.10.dist-info/METADATA
litegram-1.0.10.dist-info/WHEEL
litegram-1.0.10.dist-info/entry_points.txt
litegram-1.0.10.dist-info/licenses/LICENSE
litegram-1.0.10.dist-info/RECORD
