Metadata-Version: 2.4
Name: litegram
Version: 1.0.10
Summary: Modern and fully asynchronous framework for Telegram Bot API
Project-URL: Homepage, https://litegram.dev/
Project-URL: Documentation, https://litegram.readthedocs.io/
Project-URL: Repository, https://github.com/litegram/litegram/
Author-email: Ruslan Samoylov <ruslan@samoylov.tech>
Maintainer-email: Ruslan Samoylov <ruslan@samoylov.tech>
License-Expression: MIT
License-File: LICENSE
Keywords: api,asyncio,bot,framework,telegram,wrapper
Classifier: Development Status :: 5 - Production/Stable
Classifier: Environment :: Console
Classifier: Framework :: AsyncIO
Classifier: Intended Audience :: Developers
Classifier: Intended Audience :: System Administrators
Classifier: License :: OSI Approved :: MIT License
Classifier: Programming Language :: Python :: 3.13
Classifier: Programming Language :: Python :: 3.14
Classifier: Topic :: Communications :: Chat
Classifier: Topic :: Software Development :: Libraries :: Application Frameworks
Classifier: Topic :: Software Development :: Libraries :: Python Modules
Classifier: Typing :: Typed
Requires-Python: <3.15,>=3.13
Requires-Dist: aiofiles<26.0,>=25.1
Requires-Dist: certifi>=2026.1.4
Requires-Dist: httpx<0.29,>=0.27
Requires-Dist: litestar<3.0,>=2.19
Requires-Dist: pydantic<2.13,>=2.12
Requires-Dist: typing-extensions<=5.0,>=4.15.0
Provides-Extra: cli
Requires-Dist: litestar[cli]; extra == 'cli'
Requires-Dist: rich-click>=1.8.5; extra == 'cli'
Requires-Dist: shellingham>=1.5.4; extra == 'cli'
Provides-Extra: cryptography
Requires-Dist: litestar[cryptography]; extra == 'cryptography'
Provides-Extra: docs
Requires-Dist: furo>=2025.12.19; extra == 'docs'
Requires-Dist: markdown-include>=0.8.1; extra == 'docs'
Requires-Dist: pygments>=2.19; extra == 'docs'
Requires-Dist: pymdown-extensions>=10.20; extra == 'docs'
Requires-Dist: sphinx-autobuild>=2025.8.25; extra == 'docs'
Requires-Dist: sphinx-copybutton>=0.5.2; extra == 'docs'
Requires-Dist: sphinx-intl>=2.3; extra == 'docs'
Requires-Dist: sphinx-substitution-extensions>=2026.1.12; extra == 'docs'
Requires-Dist: sphinx>=9.1; extra == 'docs'
Requires-Dist: sphinxcontrib-towncrier>=0.5.0a0; extra == 'docs'
Requires-Dist: towncrier>=25.8.0; extra == 'docs'
Provides-Extra: fast
Requires-Dist: httptools>=0.6.4; extra == 'fast'
Requires-Dist: uvloop>=0.22.1; ((sys_platform == 'darwin' or sys_platform == 'linux') and platform_python_implementation != 'PyPy') and extra == 'fast'
Provides-Extra: i18n
Requires-Dist: babel<3,>=2.17; extra == 'i18n'
Provides-Extra: mongo
Requires-Dist: motor<3.8,>=3.7; extra == 'mongo'
Requires-Dist: pymongo<4.17,>=4.10; extra == 'mongo'
Provides-Extra: proxy
Requires-Dist: httpx-socks~=0.11; extra == 'proxy'
Provides-Extra: redis
Requires-Dist: litestar[redis]; extra == 'redis'
Provides-Extra: signature
Requires-Dist: litestar[cryptography]; extra == 'signature'
Provides-Extra: speedups
Requires-Dist: httptools>=0.6.4; extra == 'speedups'
Requires-Dist: uvloop>=0.22.1; ((sys_platform == 'darwin' or sys_platform == 'linux') and platform_python_implementation != 'PyPy') and extra == 'speedups'
